sendtelegram/__init__.py
sendtelegram/cli.py
sendtelegram/commands.py
sendtelegram-0.2.0.dist-info/LICENSE
sendtelegram-0.2.0.dist-info/METADATA
sendtelegram-0.2.0.dist-info/WHEEL
sendtelegram-0.2.0.dist-info/entry_points.txt
sendtelegram-0.2.0.dist-info/top_level.txt
sendtelegram-0.2.0.dist-info/RECORD
