Metadata-Version: 2.1
Name: sendtelegram
Version: 0.2.0
Summary: A telegram replacement for sendmail.
Home-page: https://github.com/gstracquadanio/sendtelegram
Author: Giovanni Stracquadanio
Author-email: giovanni.stracquadanio@ed.ac.uk
License: MIT
Platform: UNKNOWN
Classifier: License :: OSI Approved :: MIT License
Classifier: Programming Language :: Python :: 3
Classifier: Programming Language :: Python :: 3.6
Classifier: Programming Language :: Python :: 3.7
Classifier: Programming Language :: Python :: 3.8
Requires-Dist: requests (>=2.22)
Requires-Dist: argh (>=0.26)
